{
  "sessions": [
    {
      "id": "38d32ac0-dd21-44a7-80fd-6662e8c66c6a",
      "date": "2022-09-01",
      "meetingMinutesUrl": "https://ratsinfo.magdeburg.de/getfile.asp?id=651695&type=do"
    },
    {
      "id": "6db9a021-8b61-474c-a7e5-e5bca0eecca8",
      "date": "2022-10-06",
      "meetingMinutesUrl": "https://ratsinfo.magdeburg.de/getfile.asp?id=654594&type=do"
    },
    {
      "id": "f4a7969e-765e-481c-9ea3-343caa6b45d9",
      "date": "2022-10-10",
      "meetingMinutesUrl": "https://ratsinfo.magdeburg.de/getfile.asp?id=654425&type=do"
    },
    {
      "id": "8751aa86-95f3-40cf-a94b-972a0cccaeec",
      "date": "2022-11-10",
      "meetingMinutesUrl": "https://ratsinfo.magdeburg.de/getfile.asp?id=657312&type=do"
    },
    {
      "id": "2a54f78a-6ef5-4108-916f-3bc3c6a715d3",
      "date": "2022-11-14",
      "meetingMinutesUrl": "https://ratsinfo.magdeburg.de/getfile.asp?id=657418&type=do"
    },
    {
      "id": "e245bad0-dab3-45c1-9c77-5ed766f3790c",
      "date": "2022-12-08",
      "meetingMinutesUrl": "https://ratsinfo.magdeburg.de/getfile.asp?id=659321&type=do"
    },
    {
      "id": "fb46c1db-ed18-4270-bdee-5755e8cf7695",
      "date": "2022-12-12",
      "meetingMinutesUrl": "https://ratsinfo.magdeburg.de/getfile.asp?id=659687&type=do"
    },
    {
      "id": "795f2ca3-86c4-4b74-b569-9b2a3567d009",
      "date": "2023-01-19",
      "meetingMinutesUrl": "https://ratsinfo.magdeburg.de/getfile.asp?id=661352&type=do"
    },
    {
      "id": "797eafa1-8b4b-45ba-81df-cb8f8b43addd",
      "date": "2023-02-16",
      "meetingMinutesUrl": "https://ratsinfo.magdeburg.de/getfile.asp?id=663361&type=do"
    },
    {
      "id": "2ee4767f-67f0-44c5-b2eb-2726b95c8667",
      "date": "2023-03-16",
      "meetingMinutesUrl": "https://ratsinfo.magdeburg.de/getfile.asp?id=665698&type=do"
    },
    {
      "id": "5496fb56-be23-4680-892e-8dd385cbd569",
      "date": "2023-04-20",
      "meetingMinutesUrl": "https://ratsinfo.magdeburg.de/getfile.asp?id=668200&type=do"
    },
    {
      "id": "2b018232-41da-455e-bd31-0196210fb152",
      "date": "2023-04-24",
      "meetingMinutesUrl": "https://ratsinfo.magdeburg.de/getfile.asp?id=668587&type=do"
    },
    {
      "id": "322e2bb3-7e07-4f43-8503-5f7a701ff8b7",
      "date": "2023-05-25",
      "meetingMinutesUrl": "https://ratsinfo.magdeburg.de/getfile.asp?id=670568&type=do"
    },
    {
      "id": "338f0710-e1a4-45b5-b500-c88566fcf7b8",
      "date": "2023-05-30",
      "meetingMinutesUrl": "https://ratsinfo.magdeburg.de/getfile.asp?id=670828&type=do"
    },
    {
      "id": "941af953-2de0-468c-b992-3d3500dca263",
      "date": "2023-06-22",
      "meetingMinutesUrl": "https://ratsinfo.magdeburg.de/getfile.asp?id=672743&type=do"
    },
    {
      "id": "599c7d7f-2142-476d-b4f0-032dd28ff1bc",
      "date": "2023-06-26",
      "meetingMinutesUrl": "https://ratsinfo.magdeburg.de/getfile.asp?id=673209&type=do"
    },
    {
      "id": "3e40648c-ece8-4cd7-976d-73aadf358f07",
      "date": "2023-08-17",
      "meetingMinutesUrl": "https://ratsinfo.magdeburg.de/getfile.asp?id=676370&type=do"
    },
    {
      "id": "addad8b7-1b0a-4719-9f4c-4fbb5c761391",
      "date": "2023-08-21",
      "meetingMinutesUrl": "https://ratsinfo.magdeburg.de/getfile.asp?id=676113&type=do"
    },
    {
      "id": "d077d0f5-8dba-4a35-b5f1-945f2e50f897",
      "date": "2023-09-14",
      "meetingMinutesUrl": "https://ratsinfo.magdeburg.de/getfile.asp?id=677795&type=do"
    },
    {
      "id": "58523a6c-9048-4777-a2bf-1eaa07eadcb7",
      "date": "2023-09-18",
      "meetingMinutesUrl": "https://ratsinfo.magdeburg.de/getfile.asp?id=677935&type=do"
    },
    {
      "id": "ee190b60-7fba-4781-b17c-5d4c380a5dfb",
      "date": "2023-10-12",
      "meetingMinutesUrl": "https://ratsinfo.magdeburg.de/getfile.asp?id=680032&type=do"
    },
    {
      "id": "415e321b-3108-4e66-bddb-eb91fca7a0ee",
      "date": "2023-10-16",
      "meetingMinutesUrl": "https://ratsinfo.magdeburg.de/getfile.asp?id=680269&type=do"
    },
    {
      "id": "12f84eb0-030a-4a1a-a2d4-04217eded7ea",
      "date": "2023-11-20",
      "meetingMinutesUrl": "https://ratsinfo.magdeburg.de/getfile.asp?id=682798&type=do"
    },
    {
      "id": "c0b60de6-9f77-42de-bd54-5c0f70b82fb5",
      "date": "2023-12-07",
      "meetingMinutesUrl": "https://ratsinfo.magdeburg.de/getfile.asp?id=684309&type=do"
    },
    {
      "id": "b03bfa41-e6f6-4731-9f72-d47e08e89e6c",
      "date": "2023-12-11",
      "meetingMinutesUrl": "https://ratsinfo.magdeburg.de/getfile.asp?id=684614&type=do"
    },
    {
      "id": "a705278d-284d-4a9c-ab53-d1b90aff4ff0",
      "date": "2024-01-18",
      "meetingMinutesUrl": "https://ratsinfo.magdeburg.de/getfile.asp?id=686309&type=do"
    },
    {
      "id": "f87fdbba-7b5c-43fd-aaf7-3f503ad11107",
      "date": "2024-02-15",
      "meetingMinutesUrl": "https://ratsinfo.magdeburg.de/getfile.asp?id=688649&type=do"
    },
    {
      "id": "eb5cb434-42ef-4df5-845c-2d085ffa3275",
      "date": "2024-03-07",
      "meetingMinutesUrl": "https://ratsinfo.magdeburg.de/getfile.asp?id=689821&type=do"
    },
    {
      "id": "1fb301b8-0522-483d-86a1-941c20cffb5c",
      "date": "2024-03-11",
      "meetingMinutesUrl": "https://ratsinfo.magdeburg.de/getfile.asp?id=689818&type=do"
    }
  ],
  "fractions": [
    {
      "id": "ea9523a9-2825-427f-98b1-ee5cfc59651b",
      "name": "GRÜNE/future!",
      "seats": 11
    },
    {
      "id": "0c96deb0-8a5e-4cb7-aea7-b167a0c9f472",
      "name": "FDP/Tierschutzpartei",
      "seats": 6
    },
    {
      "id": "480fb9f1-2032-49e3-b671-7eec6265fec0",
      "name": "SPD",
      "seats": 10
    },
    {
      "id": "31c2810c-2e4f-4f2f-9636-060ff98e714a",
      "name": "AfD",
      "seats": 8
    },
    {
      "id": "c2aa86cd-7b8e-4e1c-b489-3b535f1be029",
      "name": "DIE LINKE",
      "seats": 8
    },
    {
      "id": "12c83b4a-a7ab-4965-a642-06add6a7fcd5",
      "name": "CDU",
      "seats": 10
    },
    {
      "id": "d6db336f-1f1a-4eb9-b743-1c18e39259f8",
      "name": "Gartenpartei/Tierschutzallianz",
      "seats": 3
    },
    {
      "id": "a316cf77-a957-42f4-add2-3cd6212f6389",
      "name": "Oberbürgermeisterin",
      "seats": 1
    }
  ],
  "parties": [
    {
      "id": "buendnis-90-die-gruenen",
      "name": "Bündnis 90/Die Grünen",
      "seats": 9
    },
    {
      "id": "future-magdeburg",
      "name": "future! Magdeburg",
      "seats": 2
    },
    {
      "id": "cdu",
      "name": "CDU",
      "seats": 10
    },
    {
      "id": "spd",
      "name": "SPD",
      "seats": 10
    },
    {
      "id": "afd",
      "name": "AfD",
      "seats": 8
    },
    {
      "id": "die-linke",
      "name": "DIE LINKE",
      "seats": 8
    },
    {
      "id": "gartenpartei",
      "name": "Gartenpartei",
      "seats": 2
    },
    {
      "id": "tierschutzpartei",
      "name": "Tierschutzpartei",
      "seats": 3
    },
    {
      "id": "tierschutzallianz",
      "name": "Tierschutzallianz",
      "seats": 1
    },
    {
      "id": "fdp",
      "name": "FDP",
      "seats": 3
    },
    {
      "id": "parteilos-01",
      "name": "parteilos-01",
      "seats": 1
    }
  ],
  "persons": [
    {
      "id": "alexander-pott",
      "name": "Prof.Dr. Alexander Pott",
      "fractionId": "ea9523a9-2825-427f-98b1-ee5cfc59651b",
      "partyId": "buendnis-90-die-gruenen",
      "start": null,
      "end": null
    },
    {
      "id": "julia-bohlander",
      "name": "Julia Bohlander",
      "fractionId": "ea9523a9-2825-427f-98b1-ee5cfc59651b",
      "partyId": "buendnis-90-die-gruenen",
      "start": null,
      "end": null
    },
    {
      "id": "matthias-borowiak",
      "name": "Matthias Borowiak",
      "fractionId": "ea9523a9-2825-427f-98b1-ee5cfc59651b",
      "partyId": "buendnis-90-die-gruenen",
      "start": null,
      "end": null
    },
    {
      "id": "stephan-bublitz",
      "name": "Stephan Bublitz",
      "fractionId": "ea9523a9-2825-427f-98b1-ee5cfc59651b",
      "partyId": "future-magdeburg",
      "start": null,
      "end": null
    },
    {
      "id": "juergen-canehl",
      "name": "Jürgen Canehl",
      "fractionId": "ea9523a9-2825-427f-98b1-ee5cfc59651b",
      "partyId": "buendnis-90-die-gruenen",
      "start": null,
      "end": null
    },
    {
      "id": "mathilde-lemesle",
      "name": "Mathilde Lemesle",
      "fractionId": "ea9523a9-2825-427f-98b1-ee5cfc59651b",
      "partyId": "buendnis-90-die-gruenen",
      "start": null,
      "end": null
    },
    {
      "id": "madeleine-linke",
      "name": "Madeleine Linke",
      "fractionId": "ea9523a9-2825-427f-98b1-ee5cfc59651b",
      "partyId": "buendnis-90-die-gruenen",
      "start": null,
      "end": null
    },
    {
      "id": "julia-mayer-buch",
      "name": "Julia Mayer-Buch",
      "fractionId": "ea9523a9-2825-427f-98b1-ee5cfc59651b",
      "partyId": "buendnis-90-die-gruenen",
      "start": null,
      "end": null
    },
    {
      "id": "olaf-meister",
      "name": "Olaf Meister",
      "fractionId": "ea9523a9-2825-427f-98b1-ee5cfc59651b",
      "partyId": "buendnis-90-die-gruenen",
      "start": null,
      "end": null
    },
    {
      "id": "kathrin-natho",
      "name": "Kathrin Natho",
      "fractionId": "ea9523a9-2825-427f-98b1-ee5cfc59651b",
      "partyId": "buendnis-90-die-gruenen",
      "start": null,
      "end": null
    },
    {
      "id": "mirko-stage",
      "name": "Mirko Stage",
      "fractionId": "ea9523a9-2825-427f-98b1-ee5cfc59651b",
      "partyId": "future-magdeburg",
      "start": null,
      "end": null
    },
    {
      "id": "kathrin-meyer-pinger",
      "name": "Kathrin Meyer-Pinger",
      "fractionId": "0c96deb0-8a5e-4cb7-aea7-b167a0c9f472",
      "partyId": "fdp",
      "start": null,
      "end": null
    },
    {
      "id": "burkhard-moll",
      "name": "Burkhard Moll",
      "fractionId": "0c96deb0-8a5e-4cb7-aea7-b167a0c9f472",
      "partyId": "tierschutzpartei",
      "start": null,
      "end": null
    },
    {
      "id": "stephan-papenbreer",
      "name": "Stephan Papenbreer",
      "fractionId": "0c96deb0-8a5e-4cb7-aea7-b167a0c9f472",
      "partyId": "fdp",
      "start": null,
      "end": null
    },
    {
      "id": "evelin-schulz",
      "name": "Evelin Schulz",
      "fractionId": "0c96deb0-8a5e-4cb7-aea7-b167a0c9f472",
      "partyId": "tierschutzpartei",
      "start": null,
      "end": null
    },
    {
      "id": "carola-schumann",
      "name": "Carola Schumann",
      "fractionId": "0c96deb0-8a5e-4cb7-aea7-b167a0c9f472",
      "partyId": "fdp",
      "start": null,
      "end": null
    },
    {
      "id": "barbara-jutta-tietge",
      "name": "Barbara Jutta Tietge",
      "fractionId": "0c96deb0-8a5e-4cb7-aea7-b167a0c9f472",
      "partyId": "tierschutzpartei",
      "start": null,
      "end": "2022-09-01"
    },
    {
      "id": "mirjam-karl-sy",
      "name": "Mirjam Karl-Sy",
      "fractionId": "0c96deb0-8a5e-4cb7-aea7-b167a0c9f472",
      "partyId": "tierschutzpartei",
      "start": "2022-10-06",
      "end": null
    },
    {
      "id": "norman-belas",
      "name": "Norman Belas",
      "fractionId": "480fb9f1-2032-49e3-b671-7eec6265fec0",
      "partyId": "spd",
      "start": null,
      "end": null
    },
    {
      "id": "julia-brandt",
      "name": "Julia Brandt",
      "fractionId": "480fb9f1-2032-49e3-b671-7eec6265fec0",
      "partyId": "spd",
      "start": null,
      "end": null
    },
    {
      "id": "falko-grube",
      "name": "Dr. Falko Grube",
      "fractionId": "480fb9f1-2032-49e3-b671-7eec6265fec0",
      "partyId": "spd",
      "start": null,
      "end": null
    },
    {
      "id": "christoph-abel",
      "name": "Christoph Abel",
      "fractionId": "480fb9f1-2032-49e3-b671-7eec6265fec0",
      "partyId": "spd",
      "start": null,
      "end": null
    },
    {
      "id": "karsten-koepp",
      "name": "Karsten Köpp",
      "fractionId": "480fb9f1-2032-49e3-b671-7eec6265fec0",
      "partyId": "spd",
      "start": null,
      "end": null
    },
    {
      "id": "kornelia-keune",
      "name": "Kornelia Keune",
      "fractionId": "480fb9f1-2032-49e3-b671-7eec6265fec0",
      "partyId": "spd",
      "start": null,
      "end": null
    },
    {
      "id": "steffi-meyer",
      "name": "Steffi Meyer",
      "fractionId": "480fb9f1-2032-49e3-b671-7eec6265fec0",
      "partyId": "spd",
      "start": null,
      "end": null
    },
    {
      "id": "jens-roesler",
      "name": "Jens Rösler",
      "fractionId": "480fb9f1-2032-49e3-b671-7eec6265fec0",
      "partyId": "spd",
      "start": null,
      "end": null
    },
    {
      "id": "thomas-wiebe",
      "name": "Dr. Thomas Wiebe",
      "fractionId": "480fb9f1-2032-49e3-b671-7eec6265fec0",
      "partyId": "spd",
      "start": null,
      "end": null
    },
    {
      "id": "niko-zenker",
      "name": "Dr. Niko Zenker",
      "fractionId": "480fb9f1-2032-49e3-b671-7eec6265fec0",
      "partyId": "spd",
      "start": null,
      "end": null
    },
    {
      "id": "oliver-kirchner",
      "name": "Oliver Kirchner",
      "fractionId": "31c2810c-2e4f-4f2f-9636-060ff98e714a",
      "partyId": "afd",
      "start": null,
      "end": null
    },
    {
      "id": "matthias-kleiser",
      "name": "Matthias Kleiser",
      "fractionId": "31c2810c-2e4f-4f2f-9636-060ff98e714a",
      "partyId": "afd",
      "start": null,
      "end": null
    },
    {
      "id": "hagen-kohl",
      "name": "Hagen Kohl",
      "fractionId": "31c2810c-2e4f-4f2f-9636-060ff98e714a",
      "partyId": "afd",
      "start": null,
      "end": null
    },
    {
      "id": "ronny-kumpf",
      "name": "Ronny Kumpf",
      "fractionId": "31c2810c-2e4f-4f2f-9636-060ff98e714a",
      "partyId": "afd",
      "start": null,
      "end": null
    },
    {
      "id": "christian-mertens",
      "name": "Christian Mertens",
      "fractionId": "31c2810c-2e4f-4f2f-9636-060ff98e714a",
      "partyId": "afd",
      "start": null,
      "end": null
    },
    {
      "id": "jan-moldenhauer",
      "name": "Dr. Jan Moldenhauer",
      "fractionId": "31c2810c-2e4f-4f2f-9636-060ff98e714a",
      "partyId": "afd",
      "start": null,
      "end": null
    },
    {
      "id": "frank-pasemann",
      "name": "Frank Pasemann",
      "fractionId": "31c2810c-2e4f-4f2f-9636-060ff98e714a",
      "partyId": "afd",
      "start": null,
      "end": "2024-03-07"
    },
    {
      "id": "bernd-neubauer",
      "name": "Bernd Neubauer",
      "fractionId": "31c2810c-2e4f-4f2f-9636-060ff98e714a",
      "partyId": "afd",
      "start": "2022-10-06",
      "end": null
    },
    {
      "id": "bernd-kuhnert",
      "name": "Bernd Kuhnert",
      "fractionId": "31c2810c-2e4f-4f2f-9636-060ff98e714a",
      "partyId": "afd",
      "start": "2024-03-07",
      "end": null
    },
    {
      "id": "anke-jaeger",
      "name": "Anke Jäger",
      "fractionId": "c2aa86cd-7b8e-4e1c-b489-3b535f1be029",
      "partyId": "die-linke",
      "start": null,
      "end": null
    },
    {
      "id": "tobias-baum",
      "name": "Tobias Baum",
      "fractionId": "c2aa86cd-7b8e-4e1c-b489-3b535f1be029",
      "partyId": "die-linke",
      "start": null,
      "end": null
    },
    {
      "id": "rene-hempel",
      "name": "René Hempel",
      "fractionId": "c2aa86cd-7b8e-4e1c-b489-3b535f1be029",
      "partyId": "die-linke",
      "start": null,
      "end": null
    },
    {
      "id": "dennis-jannack",
      "name": "Dennis Jannack",
      "fractionId": "c2aa86cd-7b8e-4e1c-b489-3b535f1be029",
      "partyId": "die-linke",
      "start": null,
      "end": null
    },
    {
      "id": "nadja-loesch",
      "name": "Nadja Lösch",
      "fractionId": "c2aa86cd-7b8e-4e1c-b489-3b535f1be029",
      "partyId": "die-linke",
      "start": null,
      "end": null
    },
    {
      "id": "hans-joachim-mewes",
      "name": "Hans-Joachim Mewes",
      "fractionId": "c2aa86cd-7b8e-4e1c-b489-3b535f1be029",
      "partyId": "die-linke",
      "start": null,
      "end": null
    },
    {
      "id": "oliver-mueller",
      "name": "Oliver Müller",
      "fractionId": "c2aa86cd-7b8e-4e1c-b489-3b535f1be029",
      "partyId": "die-linke",
      "start": null,
      "end": null
    },
    {
      "id": "chris-scheunchen",
      "name": "Chris Scheunchen",
      "fractionId": "c2aa86cd-7b8e-4e1c-b489-3b535f1be029",
      "partyId": "die-linke",
      "start": null,
      "end": null
    },
    {
      "id": "matthias-boxhorn",
      "name": "Matthias Boxhorn",
      "fractionId": "12c83b4a-a7ab-4965-a642-06add6a7fcd5",
      "partyId": "cdu",
      "start": null,
      "end": null
    },
    {
      "id": "bernd-heynemann",
      "name": "Bernd Heynemann",
      "fractionId": "12c83b4a-a7ab-4965-a642-06add6a7fcd5",
      "partyId": "cdu",
      "start": null,
      "end": null
    },
    {
      "id": "michael-hoffmann",
      "name": "Michael Hoffmann",
      "fractionId": "12c83b4a-a7ab-4965-a642-06add6a7fcd5",
      "partyId": "cdu",
      "start": null,
      "end": null
    },
    {
      "id": "stefanie-middendorf",
      "name": "Stefanie Middendorf",
      "fractionId": "12c83b4a-a7ab-4965-a642-06add6a7fcd5",
      "partyId": "cdu",
      "start": null,
      "end": null
    },
    {
      "id": "tim-rohne",
      "name": "Tim Rohne",
      "fractionId": "12c83b4a-a7ab-4965-a642-06add6a7fcd5",
      "partyId": "cdu",
      "start": null,
      "end": null
    },
    {
      "id": "manuel-rupsch",
      "name": "Manuel Rupsch",
      "fractionId": "12c83b4a-a7ab-4965-a642-06add6a7fcd5",
      "partyId": "cdu",
      "start": null,
      "end": null
    },
    {
      "id": "andreas-schumann",
      "name": "Andreas Schumann",
      "fractionId": "12c83b4a-a7ab-4965-a642-06add6a7fcd5",
      "partyId": "cdu",
      "start": null,
      "end": null
    },
    {
      "id": "frank-schuster",
      "name": "Frank Schuster",
      "fractionId": "12c83b4a-a7ab-4965-a642-06add6a7fcd5",
      "partyId": "cdu",
      "start": null,
      "end": null
    },
    {
      "id": "wigbert-schwenke",
      "name": "Wigbert Schwenke",
      "fractionId": "12c83b4a-a7ab-4965-a642-06add6a7fcd5",
      "partyId": "cdu",
      "start": null,
      "end": null
    },
    {
      "id": "reinhard-stern",
      "name": "Reinhard Stern",
      "fractionId": "12c83b4a-a7ab-4965-a642-06add6a7fcd5",
      "partyId": "cdu",
      "start": null,
      "end": null
    },
    {
      "id": "aila-fassl",
      "name": "Aila Fassl",
      "fractionId": "d6db336f-1f1a-4eb9-b743-1c18e39259f8",
      "partyId": "tierschutzallianz",
      "start": null,
      "end": null
    },
    {
      "id": "marcel-guderjahn",
      "name": "Marcel Guderjahn",
      "fractionId": "d6db336f-1f1a-4eb9-b743-1c18e39259f8",
      "partyId": "gartenpartei",
      "start": null,
      "end": null
    },
    {
      "id": "roland-zander",
      "name": "Roland Zander",
      "fractionId": "d6db336f-1f1a-4eb9-b743-1c18e39259f8",
      "partyId": "gartenpartei",
      "start": null,
      "end": null
    },
    {
      "id": "simone-borris",
      "name": "Simone Borris",
      "fractionId": "a316cf77-a957-42f4-add2-3cd6212f6389",
      "partyId": "parteilos-01",
      "start": null,
      "end": null
    }
  ]
}
