[
  {
    "id": 243801,
    "reference": "DS0090/24/1",
    "type": "Änderungsantrag",
    "title": "Initiierung einer Magdeburger Pflegekonferenz",
    "files": [
      {
        "id": 693543,
        "name": "Änderungsantrag",
        "url": "https://ratsinfo.magdeburg.de/getfile.asp?id=693543&type=do",
        "size": 59911
      }
    ]
  },
  {
    "id": 243802,
    "reference": "F0153/24",
    "type": "Anfrage",
    "title": "Überregionale Vermarktung der Landeshauptstadt",
    "files": [
      {
        "id": 693545,
        "name": "F0153/24 Anfrage",
        "url": "https://ratsinfo.magdeburg.de/getfile.asp?id=693545&type=do",
        "size": 63919
      }
    ]
  },
  {
    "id": 243804,
    "reference": "A0128/24/1",
    "type": "Änderungsantrag",
    "title": "Einführung des Deutschland-Tickets als Jobticket für Beschäftigte der Landeshauptstadt Magdeburg",
    "files": [
      {
        "id": 693557,
        "name": "A0128/24/1 Änderungsantrag",
        "url": "https://ratsinfo.magdeburg.de/getfile.asp?id=693557&type=do",
        "size": 14714
      }
    ]
  },
  {
    "id": 243805,
    "reference": "DS0039/24/1/1",
    "type": "Änderungsantrag",
    "title": "Aufhebungsbeschluss „FEELING EAST - Leben im Osten“",
    "files": [
      {
        "id": 693563,
        "name": "DS0039/24/1/1 Änderungsantrag",
        "url": "https://ratsinfo.magdeburg.de/getfile.asp?id=693563&type=do",
        "size": 60419
      }
    ]
  },
  {
    "id": 243806,
    "reference": "A0100/24/1",
    "type": "Änderungsantrag",
    "title": "Ausstellung Magdeburger Stadtgeschichte auch in Englisch",
    "files": [
      {
        "id": 693565,
        "name": "A0100/24/1 Änderungsantrag",
        "url": "https://ratsinfo.magdeburg.de/getfile.asp?id=693565&type=do",
        "size": 13986
      }
    ]
  },
  {
    "id": 243807,
    "reference": "F0154/24",
    "type": "Anfrage",
    "title": "Anfrage Open Data: Statistisches Jahrbuch – Digital aber mit deutlich weniger Daten?",
    "files": [
      {
        "id": 693569,
        "name": "F0154/24 Anfrage",
        "url": "https://ratsinfo.magdeburg.de/getfile.asp?id=693569&type=do",
        "size": 69177
      }
    ]
  },
  {
    "id": 243808,
    "reference": "DS0093/24/1",
    "type": "Änderungsantrag",
    "title": "Bewerbung zur Austragung der finalen Etappe der Deutschland Tour 2025 von Halle nach Magdeburg",
    "files": [
      {
        "id": 693575,
        "name": "Änderungsantrag",
        "url": "https://ratsinfo.magdeburg.de/getfile.asp?id=693575&type=do",
        "size": 62673
      }
    ]
  },
  {
    "id": 243813,
    "reference": "DS0225/24",
    "type": "Beschlussvorlage",
    "title": "Aufsichtsrat der Messe- und Veranstaltungsgesellschaft Magdeburg GmbH (MVGM)",
    "files": [
      {
        "id": 693612,
        "name": "Beschlussvorlage Stadt",
        "url": "https://ratsinfo.magdeburg.de/getfile.asp?id=693612&type=do",
        "size": 162490
      }
    ]
  },
  {
    "id": 243817,
    "reference": "DS0228/24",
    "type": "Beschlussvorlage",
    "title": "Aufsichtsrat der KLINIKUM MAGDEBURG gemeinnützige GmbH",
    "files": [
      {
        "id": 693666,
        "name": "Beschlussvorlage Stadt",
        "url": "https://ratsinfo.magdeburg.de/getfile.asp?id=693666&type=do",
        "size": 160991
      }
    ]
  },
  {
    "id": 243818,
    "reference": "DS0229/24",
    "type": "Beschlussvorlage",
    "title": "Aufsichtsrat der WOHNEN UND PFLEGEN MAGDEBURG gemeinnützige GmbH",
    "files": [
      {
        "id": 693672,
        "name": "Beschlussvorlage Stadt",
        "url": "https://ratsinfo.magdeburg.de/getfile.asp?id=693672&type=do",
        "size": 160159
      }
    ]
  },
  {
    "id": 243821,
    "reference": "A0159/23/1",
    "type": "Änderungsantrag",
    "title": "100-jährige Platane erhalten!",
    "files": [
      {
        "id": 693700,
        "name": "Änderungsantrag",
        "url": "https://ratsinfo.magdeburg.de/getfile.asp?id=693700&type=do",
        "size": 15546
      },
      {
        "id": 693701,
        "name": "GutachtenKommunalaufsicht_Platane",
        "url": "https://ratsinfo.magdeburg.de/getfile.asp?id=693701&type=do",
        "size": 2214141
      }
    ]
  },
  {
    "id": 243823,
    "reference": "DS0232/24",
    "type": "Beschlussvorlage",
    "title": "Genehmigung der Annahme von Spenden gem. § 99 Abs. 6 KVG-LSA",
    "files": [
      {
        "id": 693706,
        "name": "Beschlussvorlage Stadt",
        "url": "https://ratsinfo.magdeburg.de/getfile.asp?id=693706&type=do",
        "size": 159217
      },
      {
        "id": 693829,
        "name": "DS0232/24 Anlage Spendenannahme SR",
        "url": "https://ratsinfo.magdeburg.de/getfile.asp?id=693829&type=do",
        "size": 234497
      }
    ]
  },
  {
    "id": 243824,
    "reference": "F0155/24",
    "type": "Anfrage",
    "title": "Sicherheit Hochhaus Ziolkowskistraße",
    "files": [
      {
        "id": 693710,
        "name": "F0155/24 Anfrage",
        "url": "https://ratsinfo.magdeburg.de/getfile.asp?id=693710&type=do",
        "size": 15903
      }
    ]
  },
  {
    "id": 243825,
    "reference": "DS0233/24",
    "type": "Beschlussvorlage",
    "title": "Beschluss zur Errichtung des neuen Feuerwehrhauses der Freiwilligen Feuerwehr Magdeburg-Südost auf einem städtischen Grundstück im Schanzenweg",
    "files": [
      {
        "id": 696145,
        "name": "Beschlussvorlage Stadt",
        "url": "https://ratsinfo.magdeburg.de/getfile.asp?id=696145&type=do",
        "size": 256416
      },
      {
        "id": 697266,
        "name": "DS0233/24 Anlage Aufgabenstellung an Eb KGm vom 31.03.2020",
        "url": "https://ratsinfo.magdeburg.de/getfile.asp?id=697266&type=do",
        "size": 899595
      }
    ]
  },
  {
    "id": 243826,
    "reference": "F0156/24",
    "type": "Anfrage",
    "title": "Abfalltrennung innerhalb der Verwaltung der Landeshaupt Magdeburg",
    "files": [
      {
        "id": 693735,
        "name": "Anfrage",
        "url": "https://ratsinfo.magdeburg.de/getfile.asp?id=693735&type=do",
        "size": 64253
      }
    ]
  },
  {
    "id": 243827,
    "reference": "S0248/24",
    "type": "Stellungnahme",
    "title": "Fehlende Straßenbeleuchtung und Beschriftung an der Fahrradstraße",
    "files": [
      {
        "id": 693765,
        "name": "S0248/24 Stellungnahme",
        "url": "https://ratsinfo.magdeburg.de/getfile.asp?id=693765&type=do",
        "size": 49520
      }
    ]
  },
  {
    "id": 243828,
    "reference": "F0157/24",
    "type": "Anfrage",
    "title": "Stadtgeschichtliche Exposés",
    "files": [
      {
        "id": 693740,
        "name": "Anfrage F0157/24",
        "url": "https://ratsinfo.magdeburg.de/getfile.asp?id=693740&type=do",
        "size": 15655
      }
    ]
  },
  {
    "id": 243829,
    "reference": "F0158/24",
    "type": "Anfrage",
    "title": "Piktogramm „Vorsicht Spielende Kinder“ für die Dürerstraße und künftige Verkehrsführung in der Schneidersgarten Straße",
    "files": [
      {
        "id": 693749,
        "name": "F0158/24 Anfrage",
        "url": "https://ratsinfo.magdeburg.de/getfile.asp?id=693749&type=do",
        "size": 62657
      },
      {
        "id": 693750,
        "name": "F0158/24 Anlage Beispiele",
        "url": "https://ratsinfo.magdeburg.de/getfile.asp?id=693750&type=do",
        "size": 128938
      }
    ]
  },
  {
    "id": 243830,
    "reference": "F0159/24",
    "type": "Anfrage",
    "title": "Stromhaus am Eiskellerplatz forever oder Totgesagte leben länger",
    "files": [
      {
        "id": 693752,
        "name": "F0159/24 Anfrage",
        "url": "https://ratsinfo.magdeburg.de/getfile.asp?id=693752&type=do",
        "size": 15326
      },
      {
        "id": 693753,
        "name": "F0159/24 Anlage",
        "url": "https://ratsinfo.magdeburg.de/getfile.asp?id=693753&type=do",
        "size": 199199
      }
    ]
  },
  {
    "id": 243831,
    "reference": "S0249/24",
    "type": "Stellungnahme",
    "title": "Sanierung Neustädter See",
    "files": [
      {
        "id": 693758,
        "name": "S0249/24 Stellungnahme",
        "url": "https://ratsinfo.magdeburg.de/getfile.asp?id=693758&type=do",
        "size": 129021
      }
    ]
  },
  {
    "id": 243832,
    "reference": "DS0234/24",
    "type": "Beschlussvorlage",
    "title": "Aufsichtsrat der Magdeburger Verkehrsbetriebe GmbH & Co. KG",
    "files": [
      {
        "id": 693762,
        "name": "Beschlussvorlage Stadt",
        "url": "https://ratsinfo.magdeburg.de/getfile.asp?id=693762&type=do",
        "size": 163027
      }
    ]
  },
  {
    "id": 243836,
    "reference": "A0120/24/1",
    "type": "Änderungsantrag",
    "title": "Handwerkerparkausweis",
    "files": [
      {
        "id": 693788,
        "name": "Änderungsantrag",
        "url": "https://ratsinfo.magdeburg.de/getfile.asp?id=693788&type=do",
        "size": 17822
      }
    ]
  },
  {
    "id": 243838,
    "reference": "DS0239/24",
    "type": "Beschlussvorlage",
    "title": "Jahresabschluss 2023 der Städtische Werke Magdeburg GmbH & Co. KG",
    "files": [
      {
        "id": 693800,
        "name": "Beschlussvorlage Stadt",
        "url": "https://ratsinfo.magdeburg.de/getfile.asp?id=693800&type=do",
        "size": 225905
      },
      {
        "id": 694257,
        "name": "DS0239/24 Anlage 1 Lagebeurteilung",
        "url": "https://ratsinfo.magdeburg.de/getfile.asp?id=694257&type=do",
        "size": 325778
      },
      {
        "id": 694258,
        "name": "DS0239/24 Anlage 2 Bestätigungsvermerk",
        "url": "https://ratsinfo.magdeburg.de/getfile.asp?id=694258&type=do",
        "size": 667119
      },
      {
        "id": 694259,
        "name": "DS0239/24 Anlage 3 Bilanz 31.12.2023",
        "url": "https://ratsinfo.magdeburg.de/getfile.asp?id=694259&type=do",
        "size": 197563
      },
      {
        "id": 694260,
        "name": "DS0239/24 Anlage 4 Gewinn- und Verlustrechnung 2023",
        "url": "https://ratsinfo.magdeburg.de/getfile.asp?id=694260&type=do",
        "size": 181321
      },
      {
        "id": 694261,
        "name": "DS0239/24 Anlage 5 Lagebericht",
        "url": "https://ratsinfo.magdeburg.de/getfile.asp?id=694261&type=do",
        "size": 434909
      },
      {
        "id": 694262,
        "name": "DS0239/24 Anlage 6 Beschlussvorschläge AR",
        "url": "https://ratsinfo.magdeburg.de/getfile.asp?id=694262&type=do",
        "size": 174632
      },
      {
        "id": 694263,
        "name": "DS0239/24 Anlage 7 Konzernunterlagen",
        "url": "https://ratsinfo.magdeburg.de/getfile.asp?id=694263&type=do",
        "size": 661178
      }
    ]
  },
  {
    "id": 243839,
    "reference": "DS0240/24",
    "type": "Beschlussvorlage",
    "title": "Jahresabschluss 2023 der Städtische Werke Magdeburg Verwaltungs-GmbH",
    "files": [
      {
        "id": 693806,
        "name": "Beschlussvorlage Stadt",
        "url": "https://ratsinfo.magdeburg.de/getfile.asp?id=693806&type=do",
        "size": 181887
      },
      {
        "id": 694249,
        "name": "DS0240/24 Anlage 1 Lagebeurteilung",
        "url": "https://ratsinfo.magdeburg.de/getfile.asp?id=694249&type=do",
        "size": 305159
      },
      {
        "id": 694251,
        "name": "Ds0240/24 Anlage 2 Bestätigungsvermerk",
        "url": "https://ratsinfo.magdeburg.de/getfile.asp?id=694251&type=do",
        "size": 420522
      },
      {
        "id": 694252,
        "name": "DS0240/24 Anlage 3 Bilanz",
        "url": "https://ratsinfo.magdeburg.de/getfile.asp?id=694252&type=do",
        "size": 188017
      },
      {
        "id": 694253,
        "name": "DS0240/24 Anlage 4 Gewinn- und Verlustrechnung",
        "url": "https://ratsinfo.magdeburg.de/getfile.asp?id=694253&type=do",
        "size": 176846
      },
      {
        "id": 694254,
        "name": "DS0240/24 Anlage 5 Lagebericht",
        "url": "https://ratsinfo.magdeburg.de/getfile.asp?id=694254&type=do",
        "size": 329796
      },
      {
        "id": 694255,
        "name": "DS0240/24 Anlage 6 Beschlussvorschlag AR",
        "url": "https://ratsinfo.magdeburg.de/getfile.asp?id=694255&type=do",
        "size": 174843
      }
    ]
  },
  {
    "id": 243845,
    "reference": "S0252/24",
    "type": "Stellungnahme",
    "title": "Reinigungsintervalle auf städtischen Flächen",
    "files": [
      {
        "id": 693856,
        "name": "Stellungnahme",
        "url": "https://ratsinfo.magdeburg.de/getfile.asp?id=693856&type=do",
        "size": 60189
      }
    ]
  },
  {
    "id": 243849,
    "reference": "S0254/24",
    "type": "Stellungnahme",
    "title": "Elberadweg am Sarajevo-Ufer mit Dränbeton ausbauen",
    "files": [
      {
        "id": 694024,
        "name": "Stellungnahme",
        "url": "https://ratsinfo.magdeburg.de/getfile.asp?id=694024&type=do",
        "size": 49592
      }
    ]
  },
  {
    "id": 243856,
    "reference": "I0124/24",
    "type": "Informationsvorlage",
    "title": "Zwischeninfo Grundsatzbeschluss Leitidee Willy-Brandt-Platz",
    "files": [
      {
        "id": 694057,
        "name": "Information",
        "url": "https://ratsinfo.magdeburg.de/getfile.asp?id=694057&type=do",
        "size": 72058
      }
    ]
  },
  {
    "id": 243861,
    "reference": "I0125/24",
    "type": "Informationsvorlage",
    "title": "Magdeburger Weihnachtsmarkt GmbH - Prüfung der nochmaligen Ausschreibung des 4. Anteils",
    "files": [
      {
        "id": 694569,
        "name": "Information",
        "url": "https://ratsinfo.magdeburg.de/getfile.asp?id=694569&type=do",
        "size": 110734
      }
    ]
  },
  {
    "id": 243875,
    "reference": "DS0249/24",
    "type": "Beschlussvorlage",
    "title": "Neufassung der Parkgebührenordnung der Landeshauptstadt Magdeburg",
    "files": [
      {
        "id": 694755,
        "name": "Beschlussvorlage Stadt",
        "url": "https://ratsinfo.magdeburg.de/getfile.asp?id=694755&type=do",
        "size": 167744
      },
      {
        "id": 695280,
        "name": "DS0249/24 Anlage 3 Synopse",
        "url": "https://ratsinfo.magdeburg.de/getfile.asp?id=695280&type=do",
        "size": 138044
      },
      {
        "id": 695281,
        "name": "DS0249/24 Anlage 2 Neufassung Parkgebührenordnung",
        "url": "https://ratsinfo.magdeburg.de/getfile.asp?id=695281&type=do",
        "size": 148830
      },
      {
        "id": 695477,
        "name": "DS0249/24 Anlage 1 Übersichtsplan PSA",
        "url": "https://ratsinfo.magdeburg.de/getfile.asp?id=695477&type=do",
        "size": 9261364
      }
    ]
  },
  {
    "id": 243878,
    "reference": "A0012/24/2",
    "type": "Änderungsantrag",
    "title": "Digitalisierung der Sozialberichterstattung",
    "files": [
      {
        "id": 694490,
        "name": "Änderungsantrag",
        "url": "https://ratsinfo.magdeburg.de/getfile.asp?id=694490&type=do",
        "size": 14081
      }
    ]
  },
  {
    "id": 243880,
    "reference": "S0265/24",
    "type": "Stellungnahme",
    "title": "Einführung des Deutschland-Tickets als Jobticket für Beschäftigte der Landeshauptstadt Magdeburg",
    "files": [
      {
        "id": 694571,
        "name": "Stellungnahme",
        "url": "https://ratsinfo.magdeburg.de/getfile.asp?id=694571&type=do",
        "size": 17598
      }
    ]
  },
  {
    "id": 243881,
    "reference": "I0131/24",
    "type": "Informationsvorlage",
    "title": "Unterstützung von Familien in finanziellen Notlagen",
    "files": [
      {
        "id": 694583,
        "name": "Information",
        "url": "https://ratsinfo.magdeburg.de/getfile.asp?id=694583&type=do",
        "size": 73625
      }
    ]
  }
]